bhav/__init__.py
bhav/main.py
bhav/util.py
test/__init__.py
test/test_bhav.py
test/test_util.py
bhav-1.0.13.dist-info/LICENSE.txt
bhav-1.0.13.dist-info/METADATA
bhav-1.0.13.dist-info/WHEEL
bhav-1.0.13.dist-info/entry_points.txt
bhav-1.0.13.dist-info/top_level.txt
bhav-1.0.13.dist-info/RECORD
