Metadata-Version: 2.1
Name: bhav
Version: 1.0.13
Summary: CLI to download End of day Stock data from BSE and NSE
Home-page: https://gitlab.com/sw8fbar/bhav
Author: Ajay Sharma
Author-email: deal.ajay@gmail.com
License: LICENSE.txt
Platform: UNKNOWN
Requires-Python: >=3
Requires-Dist: Click
Requires-Dist: requests
Requires-Dist: python-dotenv
Requires-Dist: PyInquirer
Requires-Dist: flask
Requires-Dist: pandas
Requires-Dist: marshmallow
Requires-Dist: flask-cors
